ssm_parameter_store/__init__.py
ssm_parameter_store/stores.py
ssm_parameter_store/version.py
ssm_parameter_store-19.11.0.dist-info/LICENSE
ssm_parameter_store-19.11.0.dist-info/METADATA
ssm_parameter_store-19.11.0.dist-info/WHEEL
ssm_parameter_store-19.11.0.dist-info/top_level.txt
ssm_parameter_store-19.11.0.dist-info/RECORD
