Metadata-Version: 2.1
Name: ssm-parameter-store
Version: 19.11.0
Summary: Simple Python wrapper for getting values from AWS Systems Manager Parameter Store
Home-page: http://github.com/christippett/ssm-parameter-store
Author: Chris Tippett
Author-email: chris@spoon.nz
License: MIT
Platform: UNKNOWN
Classifier: Environment :: Web Environment
Classifier: Framework :: Django
Classifier: Operating System :: OS Independent
Classifier: License :: OSI Approved :: MIT License
Classifier: Programming Language :: Python
Classifier: Programming Language :: Python :: 2.7
Classifier: Programming Language :: Python :: 3.4
Classifier: Programming Language :: Python :: 3.5
Classifier: Programming Language :: Python :: 3.6
Classifier: Programming Language :: Python :: 3.7
Classifier: Programming Language :: Python :: Implementation :: PyPy
Requires-Dist: boto3
